LICENSE
MANIFEST.in
readme.md
requirements.txt
setup.py
flame_start/__init__.py
flame_start/flame_start_apps.py
flame_start/flame_start_config.py
flame_start/flame_start_exports.py
flame_start/flame_start_tools.py
flamepy_sg/__init__.py
flamepy_sg.egg-info/PKG-INFO
flamepy_sg.egg-info/SOURCES.txt
flamepy_sg.egg-info/dependency_links.txt
flamepy_sg.egg-info/top_level.txt
flamepy_sg/for_install/How_to_install_and_start.txt
flamepy_sg/for_install/__init__.py
flamepy_sg/for_install/bash_profile_Linux_a52
flamepy_sg/for_install/bash_profile_mac_stef
flamepy_sg/for_install/flame_start/__init__.py
flamepy_sg/for_install/flame_start/flame_start_apps.py
flamepy_sg/for_install/flame_start/flame_start_config.py
flamepy_sg/for_install/flame_start/flame_start_exports.py
flamepy_sg/for_install/flame_start/flame_start_tools.py
flamepy_sg/modules/__init__.py
flamepy_sg/modules/clique/__init__.py
flamepy_sg/modules/clique/_version.py
flamepy_sg/modules/clique/collection.py
flamepy_sg/modules/clique/descriptor.py
flamepy_sg/modules/clique/error.py
flamepy_sg/modules/clique/sorted_set.py
flamepy_sg/modules/yaml/__init__.py
flamepy_sg/modules/yaml/composer.py
flamepy_sg/modules/yaml/constructor.py
flamepy_sg/modules/yaml/cyaml.py
flamepy_sg/modules/yaml/dumper.py
flamepy_sg/modules/yaml/emitter.py
flamepy_sg/modules/yaml/error.py
flamepy_sg/modules/yaml/events.py
flamepy_sg/modules/yaml/loader.py
flamepy_sg/modules/yaml/nodes.py
flamepy_sg/modules/yaml/parser.py
flamepy_sg/modules/yaml/reader.py
flamepy_sg/modules/yaml/representer.py
flamepy_sg/modules/yaml/resolver.py
flamepy_sg/modules/yaml/scanner.py
flamepy_sg/modules/yaml/serializer.py
flamepy_sg/modules/yaml/tokens.py
flamepy_sg/scripts/CUA_apps.py
flamepy_sg/scripts/CUA_config.py
flamepy_sg/scripts/CUA_tools.py
flamepy_sg/scripts/Export_hook.py
flamepy_sg/scripts/__init__.py
flamepy_sg/scripts/batch_selections/.DS_Store
flamepy_sg/scripts/batch_selections/__init__.py
flamepy_sg/scripts/batch_selections/__init__.pyc
flamepy_sg/scripts/batch_selections/batch_selections_UI.py
flamepy_sg/scripts/batch_selections/batch_selections_UI.pyc
