Metadata-Version: 1.0
Name: flamepy-sg
Version: 0.0.0.17
Summary: Flame python tools
Home-page: https://github.com/xenjee/flamepy_sg
Author: Stefan Gaillot
Author-email: xenjee@gmail.com
License: Copyright (c) 2018, Stefan Gaillot
